binary_waterfall/__init__.py
binary_waterfall/core.py
binary_waterfall/dialogs.py
binary_waterfall/generators.py
binary_waterfall/outputs.py
binary_waterfall/version.yml
binary_waterfall/widgets.py
binary_waterfall/window.py
binary_waterfall/constants/__init__.py
binary_waterfall/constants/colors.py
binary_waterfall/constants/defaults.py
binary_waterfall/constants/enums.py
binary_waterfall/constants/links.py
binary_waterfall/constants/paths.py
binary_waterfall/constants/platform.py
binary_waterfall/constants/resources.py
binary_waterfall/constants/splash.py
binary_waterfall/constants/version.py
binary_waterfall/helpers/__init__.py
binary_waterfall/helpers/colors.py
binary_waterfall/helpers/general.py
binary_waterfall/helpers/images.py
binary_waterfall/helpers/qt.py
binary_waterfall/resources/back.png
binary_waterfall/resources/backC.png
binary_waterfall/resources/backH.png
binary_waterfall/resources/forward.png
binary_waterfall/resources/forwardC.png
binary_waterfall/resources/forwardH.png
binary_waterfall/resources/icon.ico
binary_waterfall/resources/icon.png
binary_waterfall/resources/mute.png
binary_waterfall/resources/pause.png
binary_waterfall/resources/pauseC.png
binary_waterfall/resources/pauseH.png
binary_waterfall/resources/play.png
binary_waterfall/resources/playC.png
binary_waterfall/resources/playH.png
binary_waterfall/resources/restart.png
binary_waterfall/resources/restartC.png
binary_waterfall/resources/restartH.png
binary_waterfall/resources/splash.jpg
binary_waterfall/resources/volume.png
binary_waterfall/resources/watermark.png
binary_waterfall-3.7.0.dist-info/LICENSE
binary_waterfall-3.7.0.dist-info/METADATA
binary_waterfall-3.7.0.dist-info/WHEEL
binary_waterfall-3.7.0.dist-info/entry_points.txt
binary_waterfall-3.7.0.dist-info/top_level.txt
binary_waterfall-3.7.0.dist-info/RECORD
