Metadata-Version: 2.1
Name: binary-waterfall
Version: 3.7.0
Summary: A Raw Data Media Player
Author-email: Ella Jameson <ellagjameson@gmail.com>
License: GNU GENERAL PUBLIC LICENSE
Project-URL: homepage, https://github.com/nimaid/binary-waterfall
Project-URL: repository, https://github.com/nimaid/binary-waterfall
Project-URL: Issues, https://github.com/nimaid/binary-waterfall/issues
Classifier: Topic :: Multimedia
Classifier: Topic :: Multimedia :: Graphics
Classifier: Topic :: Multimedia :: Graphics :: Graphics Conversion
Classifier: Topic :: Multimedia :: Graphics :: Viewers
Classifier: Topic :: Multimedia :: Sound/Audio
Classifier: Topic :: Multimedia :: Sound/Audio :: Conversion
Classifier: Topic :: Multimedia :: Sound/Audio :: Players
Classifier: Topic :: Multimedia :: Video
Classifier: Topic :: Multimedia :: Video :: Conversion
Classifier: Topic :: Multimedia :: Video :: Display
License-File: LICENSE
Requires-Dist: pyyaml
Requires-Dist: Pillow
Requires-Dist: PyQt5
Requires-Dist: pydub
Requires-Dist: moviepy
Requires-Dist: proglog
